README.rst
setup.cfg
setup.py
rdo/__init__.py
rdo/cmd.py
rdo/config.py
rdo/log.py
rdo.egg-info/PKG-INFO
rdo.egg-info/SOURCES.txt
rdo.egg-info/dependency_links.txt
rdo.egg-info/entry_points.txt
rdo.egg-info/not-zip-safe
rdo.egg-info/pbr.json
rdo.egg-info/top_level.txt